nanourls/__init__.py
nanourls/config.py
nanourls/db.py
nanourls/shortener.py
nanourls-0.1.0.dist-info/licenses/LICENSE
nanourls-0.1.0.dist-info/METADATA
nanourls-0.1.0.dist-info/WHEEL
nanourls-0.1.0.dist-info/top_level.txt
nanourls-0.1.0.dist-info/RECORD
